<?xml version="1.0" encoding="UTF-8"?>
<page  login-required="true" xmlns="http://jboss.com/products/seam/pages"
      xmlns:xsi="http://www.w3.org/2001/XMLSchema-instance"
      xsi:schemaLocation="http://jboss.com/products/seam/pages http://jboss.com/products/seam/pages-2.2.xsd">
      
   <param name="firstResult" value="#{ufficioList.firstResult}"/>
   <param name="order" value="#{ufficioList.order}"/>
   <param name="from"/>
   <param name="descrizione" value="#{ufficioList.ufficio.descrizione}"/>
   <param name="telefono" value="#{ufficioList.ufficio.telefono}"/>
   <param name="fax" value="#{ufficioList.ufficio.fax}"/>
   <param name="email" value="#{ufficioList.ufficio.email}"/>
   <param name="nome" value="#{ufficioList.ufficio.nome}"/>
   <param name="fax1" value="#{ufficioList.ufficio.fax1}"/>

</page>
